{"name":"node127","children":[{"name":"null xmlid extension"},{"name":"node126","children":[{"name":"device carotid artery"},{"name":"node125","children":[{"name":"node123","children":[{"name":"datapoint uid detected"},{"name":"node122","children":[{"name":"log content authorize"},{"name":"node121","children":[{"name":"trunk version latest"},{"name":"node120","children":[{"name":"completion block blocks"},{"name":"node119","children":[{"name":"ehr format medication"},{"name":"node118","children":[{"name":"node115","children":[{"name":"online wado nfc"},{"name":"coding huffman diff"}]},{"name":"node117","children":[{"name":"handle mule opencv"},{"name":"relationship build implementation"}]}]}]}]}]}]}]},{"name":"node124","children":[{"name":"sleep total deep"},{"name":"node116","children":[{"name":"node113","children":[{"name":"sample volume samples"},{"name":"node98","children":[{"name":"xml output input"},{"name":"node53","children":[{"name":"data pixel change"},{"name":"node12","children":[{"name":"data read application"},{"name":"data user record"}]}]}]}]},{"name":"node114","children":[{"name":"component pid connected"},{"name":"node112","children":[{"name":"send receive biztalk"},{"name":"node111","children":[{"name":"node105","children":[{"name":"window change level"},{"name":"extracted window width"}]},{"name":"node110","children":[{"name":"node106","children":[{"name":"blood pressure glucose"},{"name":"node103","children":[{"name":"source category wrapper"},{"name":"node100","children":[{"name":"node89","children":[{"name":"calory active burned"},{"name":"button energy click"}]},{"name":"node95","children":[{"name":"label itk image"},{"name":"node87","children":[{"name":"session activity recorded"},{"name":"node79","children":[{"name":"node71","children":[{"name":"healthkit ios swift"},{"name":"node65","children":[{"name":"watch apple health"},{"name":"background app delivery"}]}]},{"name":"node77","children":[{"name":"node74","children":[{"name":"node61","children":[{"name":"node16","children":[{"name":"file dicom files"},{"name":"file read text"}]},{"name":"node36","children":[{"name":"dicom write file"},{"name":"node26","children":[{"name":"dicom image machine"},{"name":"node15","children":[{"name":"dicom image series"},{"name":"node9","children":[{"name":"image dicom display"},{"name":"dicom image jpeg"}]}]}]}]}]},{"name":"node69","children":[{"name":"heart rate data"},{"name":"node60","children":[{"name":"node38","children":[{"name":"search query server"},{"name":"node27","children":[{"name":"server connection client"},{"name":"node25","children":[{"name":"server instance local"},{"name":"server retrieve series"}]}]}]},{"name":"node56","children":[{"name":"node31","children":[{"name":"patient information adt"},{"name":"patient practitioner multiple"}]},{"name":"node51","children":[{"name":"profile element extension"},{"name":"node34","children":[{"name":"json fhir java"},{"name":"node10","children":[{"name":"fhir resource bundle"},{"name":"fhir resource encounter"}]}]}]}]}]}]}]},{"name":"node75","children":[{"name":"mirth connect channel"},{"name":"node58","children":[{"name":"api fitness sign"},{"name":"node23","children":[{"name":"google fit activity"},{"name":"node8","children":[{"name":"google fit api"},{"name":"google api fit"}]}]}]}]}]}]}]}]}]}]}]},{"name":"node109","children":[{"name":"node102","children":[{"name":"callback url nokia"},{"name":"lab represent order"}]},{"name":"node108","children":[{"name":"check evildicom added"},{"name":"node107","children":[{"name":"store cloud content"},{"name":"node104","children":[{"name":"context loading bnf"},{"name":"node101","children":[{"name":"header error biztalk"},{"name":"node99","children":[{"name":"problem dataset speed"},{"name":"node97","children":[{"name":"marker dot overlay"},{"name":"node96","children":[{"name":"loop make today"},{"name":"node94","children":[{"name":"node90","children":[{"name":"determine end roi"},{"name":"apache camel sample"}]},{"name":"node93","children":[{"name":"study modality annotation"},{"name":"node92","children":[{"name":"node86","children":[{"name":"dicom command dcmtk"},{"name":"transfer syntax jpeg"}]},{"name":"node91","children":[{"name":"height upload page"},{"name":"node88","children":[{"name":"fhir extension resource"},{"name":"node85","children":[{"name":"node80","children":[{"name":"frame date multi"},{"name":"node78","children":[{"name":"structure time values"},{"name":"node76","children":[{"name":"node46","children":[{"name":"obx segment message"},{"name":"node35","children":[{"name":"segment message field"},{"name":"node20","children":[{"name":"message parse hapi"},{"name":"message send messages"}]}]}]},{"name":"node73","children":[{"name":"distance calculate number"},{"name":"node72","children":[{"name":"order event training"},{"name":"node70","children":[{"name":"multiple single wondering"},{"name":"node68","children":[{"name":"node49","children":[{"name":"dcm image che"},{"name":"node40","children":[{"name":"image bit pixel"},{"name":"node39","children":[{"name":"image size dataset"},{"name":"image registration mask"}]}]}]},{"name":"node67","children":[{"name":"node62","children":[{"name":"reference dll appointment"},{"name":"niftynet model trained"}]},{"name":"node66","children":[{"name":"node63","children":[{"name":"character field input"},{"name":"slice view position"}]},{"name":"node64","children":[{"name":"user ccda filter"},{"name":"node59","children":[{"name":"node54","children":[{"name":"application healthvault app"},{"name":"node45","children":[{"name":"framework application requirement"},{"name":"medical imaging alternative"}]}]},{"name":"node57","children":[{"name":"attribute entry toolkit"},{"name":"node55","children":[{"name":"node48","children":[{"name":"oauth api token"},{"name":"node44","children":[{"name":"notification information action"},{"name":"node41","children":[{"name":"researchkit swift research"},{"name":"generated java generate"}]}]}]},{"name":"node52","children":[{"name":"database sql store"},{"name":"node50","children":[{"name":"array string numpy"},{"name":"node47","children":[{"name":"location open source"},{"name":"node43","children":[{"name":"node37","children":[{"name":"node32","children":[{"name":"node28","children":[{"name":"library gdcm vtk"},{"name":"node24","children":[{"name":"access option setting"},{"name":"node22","children":[{"name":"node13","children":[{"name":"web java application"},{"name":"application implemented written"}]},{"name":"node19","children":[{"name":"node6","children":[{"name":"error issue version"},{"name":"node5","children":[{"name":"error line remove"},{"name":"error problem solve"}]}]},{"name":"node18","children":[{"name":"reference standard field"},{"name":"node14","children":[{"name":"access appreciated data"},{"name":"node11","children":[{"name":"time steps daily"},{"name":"node7","children":[{"name":"method missing program"},{"name":"node4","children":[{"name":"question system solution"},{"name":"node3","children":[{"name":"documentation values find"},{"name":"node2","children":[{"name":"find work fine"},{"name":"node1","children":[{"name":"create information idea"},{"name":"result query work"}]}]}]}]}]}]}]}]}]}]}]}]},{"name":"node30","children":[{"name":"device android sensor"},{"name":"node29","children":[{"name":"request response body"},{"name":"service call client"}]}]}]},{"name":"node33","children":[{"name":"workout watch session"},{"name":"node21","children":[{"name":"health app kit"},{"name":"node17","children":[{"name":"healthkit query delete"},{"name":"app healthkit health"}]}]}]}]},{"name":"node42","children":[{"name":"convert format object"},{"name":"document cda xml"}]}]}]}]}]}]}]}]}]}]}]}]}]}]}]}]}]}]},{"name":"node84","children":[{"name":"view controller task"},{"name":"node83","children":[{"name":"measurement unit observation"},{"name":"node82","children":[{"name":"string base system"},{"name":"node81","children":[{"name":"php notification low"},{"name":"node side tree"}]}]}]}]}]}]}]}]}]}]}]}]}]}]}]}]}]}]}]}]}]}]}]}]}]}]}]}
